{
  "$schema": "https://raw.githubusercontent.com/dotnet/Nerdbank.GitVersioning/master/src/NerdBank.GitVersioning/version.schema.json",
  "version": "4.6.1-preview.{height}",
  "assemblyVersion": {
    "precision": "revision"
  },
  "semVer1NumericIdentifierPadding": 3,
  "nuGetPackageVersion": {
    "semVer": 2.0
  },
  "publicReleaseRefSpec": [
    "^refs/heads/master$",
    "^refs/heads/nanoframework$",
    "^refs/heads/v\\d+(?:\\.\\d+)?$"
  ],
  "cloudBuild": {
    "setAllVariables": true,
    "buildNumber": null
  },
  "release": {
    "branchName": "release-v{version}",
    "versionIncrement": "build",
    "firstUnstableTag": "preview"
  }
}